{"ZP91RFv8gaKL0CjFn/rWmQ==":"sscrimea_shapka2018-1590x400.jpg","hz2EQWsqW6bf+A2jrxW2eg==":"sscrimea_shapka2018-1-1590x400.jpg","Os1hpkyKHdJTZJYYSjSiXg==":"01.jpg","Q8kyWdiPLYJ/4F1Ss+9IyA==":"03.jpg","HoeEF4HfT9nMa9Cg+v0y1w==":"02.jpg","D/MJwuutwIhlmcioKCvGqA==":"04.jpg","0OOE1Usrtktm437Z/qTMRQ==":"background2.jpg","4SbdRea/VQqj98n2Y4SKzw==":"1-552x552.jpg","KQx+E7SlFKFiWn8Y6hW/0A==":"4-552x552.jpg","bL7yc0ME/HtaGDNpTt9M3g==":"4-1-552x552.jpg","DGB3R3nFNtlnhwLBRTWomw==":"img-5872-450x450.jpg","D7RU6jrhZ4hvt2UdlfpuaQ==":"1-550x550.jpg","xl4sUwEqj3t5fWRd5anIVQ==":"1-1-550x550.jpg","hz03X9QWmL9u4CIk1bIbXA==":"img-5901-552x551.jpg","O/j9trAi3oa9aINu2A5jYQ==":"iphone_se-552x552.jpg","kVI2+eC6tu02CHAh5h7pYQ==":"iphone_se-1-552x552.jpg","5TGWffJfLh9De+0Q569ihw==":"iphone_se-2-552x552.jpg","ladS1yjMPQppB8TgD5lGMg==":"iphone_se-3-552x552.jpg","Un6y/6nsoiKi85OKrJc7Iw==":"1-2-550x550.jpg","27kHMInsVG8q+isYKhFXlQ==":"iphone_se-4-552x552.jpg","ESrZltR8Uu9fdYj+4MUf7A==":"jntkxinka90-552x414.jpg","IQH5NunEPDRrH8ToWziLRA==":"jntkxinka90-1-552x414.jpg","5OCmkbbZtJfG2RDjbv6CXA==":"jntkxinka90-2-552x414.jpg","0/PwBhJyFYYO6GAVxUelww==":"jntkxinka90-3-552x414.jpg","C3d0x1XSwLwLOZRPxDBG+Q==":"jntkxinka90-4-552x414.jpg","cVDwO2e6+mOF3kAhMsIzJQ==":"jntkxinka90-5-552x414.jpg","XD6hDCnLU6ROI4U3+rdSEg==":"jntkxinka90-6-552x414.jpg","dTMuXSbAWbVqhCRdRF3J9A==":"jntkxinka90-7-552x414.jpg","CaNx82UqldbQXbL5qDZQ4g==":"jntkxinka90-8-552x414.jpg","QeBBfj+M31GNr1KDqta0dg==":"img-5797-552x552.jpg","T7poGqD5+jPCB6+9/Aa+SQ==":"500_500_productgfx_6c5ec870719f6b3c840a80127bef337c-500x500.jpg","a8A0RNulkqvHfCd4MFuDPg==":"copy-of-apple-iphone-6-plus-64gb-space-grey-171073-552x552.jpg","zPqlVhHsvIhE5GqM7oSW3Q==":"fcbfsyfzjuq-466x466.jpg","db7NlbrXZch2SZx8HNAgqA==":"fcbfsyfzjuq-1-466x466.jpg","th1d91EhqBKffp/tVoZn+Q==":"apple-iphone-5s-32-go-argent-552x552.jpg","zW8G6rr8RbtGiU+5GtXAGw==":"apple-iphone-5s-32-go-argent-1-552x552.jpg","FiqyWj8C1QdtNbzWDJDp8A==":"apple-iphone-5s-32-go-argent-2-552x552.jpg","fTUShBa8EqbotRc3WbSdnw==":"apple-iphone-5s-32-go-argent-3-552x552.jpg","qSNs6mY019yt4sblL6Rg1Q==":"1-1-552x552.jpg","n9JndVilGylpQQkGkLsdGA==":"1-2-552x552.jpg","OA4xDfqVPvSauOkB7TvhsQ==":"1-3-552x552.jpg","8VQbT7IUi2SDwhzAlbgIyA==":"1-4-552x552.jpg","wQKfhbOskRR4h5fnEgvkow==":"iphone_se-5-552x552.jpg","ynLzdUTF0Ad8VrUE1JHCYg==":"iphone_se-6-552x552.jpg","mZpawl19+f+4/4gMb0Z3Fw==":"jntkxinka90-9-552x414.jpg","afPHDPy3CgCYutuUqsf/vw==":"%D1%81%D0%BC%D0%B0%D1%80%D1%82%D1%81%D1%82%D0%BE%D1%802018_%D0%BD%D0%BE%D1%8F%D0%B1%D1%80%D1%8C-600x533.png","QRU7VsX3ZLRh6jVbohz3zg==":"%D1%81%D0%BC%D0%B0%D1%80%D1%82%D1%81%D1%82%D0%BE%D1%802018_%D0%BD%D0%BE%D1%8F%D0%B1%D1%80%D1%8C-122x108.png","MqLUtgob24czD9ZQHSCIxw==":"sscrimea_loo_2000x2000_2018_new-138x138.png","orc2qf6VhDLSPRCEMTR9NQ==":"sscrimea_shapka2018-122x31.jpg","3D9b9nl2Oe2kehx0NuXJIw==":"sscrimea_loo_2000x2000_2018_new-478x478.png","HwtnBK0kewGysUSp0RsRWQ==":"%D0%9D%D0%BE%D0%B2%D1%8B%D0%B9%20%D0%BB%D0%BE%D0%B3%D0%BE%D1%82%D0%B8%D0%BF%202018%20smartstore%20%D0%9A%D1%80%D1%8B%D0%BC%20(png)3000%D1%853000-2526x2526.png","cK+3kXsXw2Pa5HynG6Gxdw==":"%D0%9D%D0%BE%D0%B2%D1%8B%D0%B9%20%D0%BB%D0%BE%D0%B3%D0%BE%D1%82%D0%B8%D0%BF%202018%20smartstore%20%D0%9A%D1%80%D1%8B%D0%BC%20(png)-1736x1736.png","Rnz5ADI6MdMtyu6md1mYgw==":"smartstore_%D0%9A%D0%A0%D0%AB%D0%9C_003_color2_%D0%A8%D0%90%D0%9F%D0%9A%D0%90-2018-1590x400.jpg","u5yzLRDaIinxCbMXuJIBVw==":"%D0%9D%D0%BE%D0%B2%D1%8B%D0%B9%20%D0%BB%D0%BE%D0%B3%D0%BE%D1%82%D0%B8%D0%BF%202018%20smartstore%20%D0%9A%D1%80%D1%8B%D0%BC%20(png)1590x400shapka-1590x400.png","WqJfPHD/nOmfZ3d3hVcicQ==":"%D0%9D%D0%BE%D0%B2%D1%8B%D0%B9%20%D0%BB%D0%BE%D0%B3%D0%BE%D1%82%D0%B8%D0%BF%202018%20smartstore%20%D0%9A%D1%80%D1%8B%D0%BC%20(png)%20%D0%BA%D1%80%D1%83%D0%B3001%D1%87%D1%91%D1%80%D0%BD%D1%8B%D0%B9-122x122.png","XXpGirT0ayNkyR/rp9UZDg==":"%D0%9D%D0%BE%D0%B2%D1%8B%D0%B9%20%D0%BB%D0%BE%D0%B3%D0%BE%D1%82%D0%B8%D0%BF%202018%20smartstore%20%D0%9A%D1%80%D1%8B%D0%BC%20(jpg)white1590x400shapka-1590x400.jpg","nf9h6IE1oRZt9diQdw9ShQ==":"%D0%9D%D0%BE%D0%B2%D1%8B%D0%B9%20%D0%BB%D0%BE%D0%B3%D0%BE%D1%82%D0%B8%D0%BF%202018%20smartstore%20%D0%9A%D1%80%D1%8B%D0%BC%20(jpg)white1590x400shapka-122x31.jpg","pCu7b9rUSgJJGtx5GyYwfA==":"%D0%9D%D0%BE%D0%B2%D1%8B%D0%B9%20%D0%BB%D0%BE%D0%B3%D0%BE%D1%82%D0%B8%D0%BF%202018%20smartstore%20%D0%9A%D1%80%D1%8B%D0%BC%20(png)-478x478.png","jOKMCy4mSzD/2uDH9Ex5hQ==":"%D0%9D%D0%BE%D0%B2%D1%8B%D0%B9%20%D0%BB%D0%BE%D0%B3%D0%BE%D1%82%D0%B8%D0%BF%202018%20smartstore%20%D0%9A%D1%80%D1%8B%D0%BC%20(png)3000%D1%853000-122x122.png","9/SFdqROtTkSC8O0Egbapg==":"smartstore_%D0%9A%D0%A0%D0%AB%D0%9C_003_color2_%D0%A8%D0%90%D0%9F%D0%9A%D0%90-2018-780x196.jpg","KK5jSDeB86XoGmHq2GxC8g==":"%D0%9D%D0%BE%D0%B2%D1%8B%D0%B9%20%D0%BB%D0%BE%D0%B3%D0%BE%D1%82%D0%B8%D0%BF%202018%20smartstore%20%D0%9A%D1%80%D1%8B%D0%BC%20(png)1590x400shapka-484x122.png","pwNYjiUx+CX656PdHKx39w==":"big-552x520.jpg","HKtnknI2yc3IS1JTBoz5eQ==":"s7edge-552x552.jpg","NL16G5M7UHJMLT8YN5COlA==":"s8-552x552.jpg","0dz0L46wH2SOzUuaj086Fw==":"s8+-552x552.jpg","6/GoFtFXc5kAzOCVX2rbOQ==":"1jiwjxwe1gs-552x552.jpg","9LxRfOR6Z515ogfS8mcRzg==":"21008-home_default-552x690.jpg","Wiyh9MUDKaA+WOYi4DsiKA==":"1jiwjxwe1gs-1-552x552.jpg","s0Ewf0YcL7VtQWwg4PhJcA==":"1jiwjxwe1gs-2-552x552.jpg","UjX5HuqQaiVXoJAJ6q+nRA==":"1jiwjxwe1gs-3-552x552.jpg","iWldyQy6YS3fmxFE1jb99g==":"1jiwjxwe1gs-4-552x552.jpg","9fdde2saCrtc2nWYatmKbg==":"1jiwjxwe1gs-5-552x552.jpg","Vj73RJYjkDu+p6lq64lLjw==":"1jiwjxwe1gs-6-552x552.jpg","MpmRn98gwfUJ1hIVm21G+g==":"4-430x430.jpg","u89nXr3EREMx3ZLM+kIo7w==":"4-1-430x430.jpg","CWVPORLeXy/EOf8S0RGLug==":"1-430x430.jpg","15gyG3d5btdc+uvz4DDHGw==":"1-1-430x430.jpg","t9LJ6EV5SWZLHOZA4dHDRQ==":"3-430x430.jpg","BiPsTwfTtF8BWvL9od/vYw==":"11354218070046-430x430.jpg","+6dCNohVasQncokFQcICqg==":"11354218070046-1-430x430.jpg","O3ZUz1m1Cl6gAs0r7fUfTg==":"11354218070046-2-430x430.jpg","lN6VlVf5vsbCg6TFlCKuzg==":"11354218070046-3-430x430.jpg","BlaEGgLYTMdLR3vn0qj2VA==":"11354218070046-4-430x430.jpg","gSpvXL6LhjWMZGosKDfngQ==":"img_13044_da0d6c2a70660b21b706499a304c512d-20-430x430.jpg","q7NuhFsfrntPXViCHHBQ5g==":"img_13044_da0d6c2a70660b21b706499a304c512d-21-430x430.jpg","UIhdAf62gWhUncUs0nouYQ==":"img_13044_da0d6c2a70660b21b706499a304c512d-22-430x430.jpg","H9YsxzttbBEe0JRRU6jWKQ==":"original-1-i78plus-552x552.jpg","zqTnjWPZC1m9TckHhTKsew==":"funda-silicone-cover-original-samsung-s8-s8-plus-envio-d_nq_np_882678-mla25870910601_082017-f-552x454.jpg","94uxymMc1dH/P8jEbG0nGQ==":"funda-silicone-cover-original-samsung-s8-s8-plus-envio-d_nq_np_882678-mla25870910601_082017-f-1-552x454.jpg","y/7cbtPZx5a8KZLCBCo0bg==":"funda-silicone-cover-original-samsung-s8-s8-plus-envio-d_nq_np_882678-mla25870910601_082017-f-2-552x454.jpg","qiRiRP/Z3wop6PrpJpEbew==":"funda-silicone-cover-original-samsung-s8-s8-plus-envio-d_nq_np_882678-mla25870910601_082017-f-3-552x454.jpg","iR7pWbRuDrNds7hglOb80g==":"imax-iphone-6-6s-3d-zaschitnoe-steklo-0.15mm-white12-552x552.jpg","eyBZEWP0ffWDf/lcSkIQLw==":"pelicula_protetora_3d_em_vidro_temperado_com_0_23mm_para_iphone_8_8_plus_201000146_1-20171108145249-552x552.jpg","7i97Xh6jrx4gUqS6qOo2ag==":"2db4fda-12a7-44e0-88f3-0d22c2daa4fb_2.02d5f39a245a222f8de1ff5484b1d927-552x552.jpg","S/TXQTUOckhk6y+QSLbopQ==":"funda-silicone-cover-original-samsung-s8-s8-plus-envio-d_nq_np_882678-mla25870910601_082017-f-4-552x454.jpg","TIJ+2sCgXMffYX9s0JNo0g==":"funda-silicone-cover-original-samsung-s8-s8-plus-envio-d_nq_np_882678-mla25870910601_082017-f-5-552x454.jpg"}